citydata/__init__.py
citydata/citydata.py
citydata-0.0.4.dist-info/LICENSE
citydata-0.0.4.dist-info/METADATA
citydata-0.0.4.dist-info/WHEEL
citydata-0.0.4.dist-info/top_level.txt
citydata-0.0.4.dist-info/RECORD
