Metadata-Version: 2.1
Name: citydata
Version: 0.0.4
Summary: get the Chinese city data
Home-page: https://github.com/Darley-Wey/citydata
Author: Darley-Wey
Author-email: darley.wey@gmail.com
Classifier: Programming Language :: Python :: 3
Classifier: License :: OSI Approved :: MIT License
Classifier: Operating System :: OS Independent
Requires-Python: >=3.8
License-File: LICENSE
